<?xml version="1.0" encoding="UTF-8"?>
<objects serializationModel="Studio.01.10.00">
    <object class="AudioFile" id="{511cd05c-a1a2-4bb4-9a41-ec607ede4bff}">
        <property name="assetPath">
            <value>Generic_Sound_Character_Bloodrip2.wav</value>
        </property>
        <property name="frequencyInKHz">
            <value>96</value>
        </property>
        <property name="channelCount">
            <value>2</value>
        </property>
        <property name="length">
            <value>4.0800000000000001</value>
        </property>
        <relationship name="masterAssetFolder">
            <destination>{3a30082e-ba72-490e-b2e2-08fe33ecf383}</destination>
        </relationship>
    </object>
</objects>
