<?xml version="1.0" encoding="UTF-8"?>
<objects serializationModel="Studio.01.10.00">
    <object class="AudioFile" id="{a121aa36-0938-44d8-9a48-b9a23615c00f}">
        <property name="assetPath">
            <value>Generic_Sound_Character_Auraofdecay.wav</value>
        </property>
        <property name="isStreaming">
            <value>true</value>
        </property>
        <property name="frequencyInKHz">
            <value>96</value>
        </property>
        <property name="channelCount">
            <value>2</value>
        </property>
        <property name="length">
            <value>16.367999999999999</value>
        </property>
        <relationship name="masterAssetFolder">
            <destination>{3a30082e-ba72-490e-b2e2-08fe33ecf383}</destination>
        </relationship>
    </object>
</objects>
